polarion_tools_common/__init__.py
polarion_tools_common/configuration.py
polarion_tools_common/utils.py
polarion_tools_common-1.1.0.dist-info/METADATA
polarion_tools_common-1.1.0.dist-info/WHEEL
polarion_tools_common-1.1.0.dist-info/top_level.txt
polarion_tools_common-1.1.0.dist-info/RECORD
