Metadata-Version: 2.1
Name: polarion-tools-common
Version: 1.1.0
Summary: Common utilities for Polarion tools
Home-page: https://gitlab.com/mkourim/polarion-tools-common
Author: Martin Kourim
Author-email: mkourim@redhat.com
License: MIT
Keywords: polarion,testing
Platform: UNKNOWN
Classifier: Development Status :: 3 - Alpha
Classifier: Topic :: Software Development :: Libraries :: Python Modules
Classifier: Topic :: Software Development :: Testing
Classifier: License :: OSI Approved :: MIT License
Classifier: Programming Language :: Python :: 3.5
Classifier: Programming Language :: Python :: 3.6
Classifier: Programming Language :: Python :: 3.7
Classifier: Intended Audience :: Developers
Requires-Dist: pyyaml
